{
  "name": "Independence in Probability",
  "children": [
    {
      "name": "Recap: Conditional Probability",
      "children": [
        {
          "name": "Notation: P(A|B)"
        },
        {
          "name": "Intersection divided by P(B)"
        },
        {
          "name": "Law of Total Probability"
        },
        {
          "name": "Tree Diagrams"
        }
      ]
    },
    {
      "name": "Definition of Independence",
      "children": [
        {
          "name": "Formula: P(A|B) = P(A)"
        },
        {
          "name": "B does not affect A"
        },
        {
          "name": "P(B) = 0 case"
        },
        {
          "name": "Empty/Full events"
        }
      ]
    },
    {
      "name": "Intuition and Scenarios",
      "children": [
        {
          "name": "Monty Hall Problem",
          "children": [
            {
              "name": "Revealed doors vs. Door 1"
            },
            {
              "name": "Switching strategy"
            }
          ]
        },
        {
          "name": "Disjoint Events",
          "children": [
            {
              "name": "A intersect B = empty"
            },
            {
              "name": "Typically not independent"
            }
          ]
        },
        {
          "name": "Subset Events",
          "children": [
            {
              "name": "B is subset of A"
            },
            {
              "name": "P(A|B) = 1"
            }
          ]
        }
      ]
    },
    {
      "name": "Product Rule",
      "children": [
        {
          "name": "P(A ∩ B) = P(A) * P(B)"
        },
        {
          "name": "Symmetric Relation"
        },
        {
          "name": "Equivalent to P(B|A) = P(B)"
        }
      ]
    },
    {
      "name": "Multiple Events",
      "children": [
        {
          "name": "Pairwise Independence",
          "children": [
            {
              "name": "Every pair is independent"
            }
          ]
        },
        {
          "name": "Mutual Independence",
          "children": [
            {
              "name": "Stronger notion"
            },
            {
              "name": "Subset intersections"
            },
            {
              "name": "Product rule for n events"
            }
          ]
        }
      ]
    },
    {
      "name": "Coin Flipping Examples",
      "children": [
        {
          "name": "Independent Fair Coins"
        },
        {
          "name": "Weighted Coins (p and q)"
        },
        {
          "name": "Same-outcome Event (S)"
        },
        {
          "name": "Real-world Coin Physics"
        }
      ]
    },
    {
      "name": "Birthday Paradox",
      "children": [
        {
          "name": "Duplicate Birthdays"
        },
        {
          "name": "Pigeonhole vs. Probabilistic"
        },
        {
          "name": "Break-even point: n=23"
        },
        {
          "name": "Approximation using e"
        },
        {
          "name": "Square root of d behavior"
        },
        {
          "name": "Hashing and Cryptography"
        }
      ]
    },
    {
      "name": "Gambler's Fallacy",
      "children": [
        {
          "name": "Memoryless flips"
        },
        {
          "name": "Human Psychology vs. Math"
        },
        {
          "name": "Bayesian Model: Fair vs. Cheating"
        }
      ]
    }
  ]
}